autoclean/__init__.py
autoclean/cleaner.py
autoclean/imputation.py
autoclean/outliers.py
autoclean/reports.py
autocleanss-0.1.3.dist-info/licenses/LICENSE.txt
autocleanss-0.1.3.dist-info/METADATA
autocleanss-0.1.3.dist-info/WHEEL
autocleanss-0.1.3.dist-info/top_level.txt
autocleanss-0.1.3.dist-info/RECORD
