Metadata-Version: 2.4
Name: autocleanss
Version: 0.1.3
Summary: An advanced and automated data cleaning toolkit for Python.
Author-email: SUDIPTA BISWAS <sudiptabiswas394@gmail.com>
License: MIT License
Project-URL: Homepage, https://github.com/sudipta9749/autocleanss
Project-URL: Bug Tracker, https://github.com/sudipta9749/autocleanss/issues
Keywords: data cleaning,data preprocessing,machine learning,automation,pandas
Classifier: Programming Language :: Python :: 3
Classifier: Operating System :: OS Independent
Classifier: Topic :: Scientific/Engineering :: Information Analysis
Requires-Python: >=3.8
License-File: LICENSE.txt
Requires-Dist: pandas>=1.3.0
Requires-Dist: numpy>=1.20.0
Requires-Dist: scikit-learn>=1.0.0
Requires-Dist: matplotlib>=3.4.0
Requires-Dist: seaborn>=0.11.0
Requires-Dist: jinja2>=3.0.0
Requires-Dist: setuptools>=61.0
Dynamic: license-file
